syndp/__init__.py
syndp/bounded_laplace_mechanism.py
syndp/functions.py
syndp/laplace_mechanism.py
syndp/original_timedp.py
syndp/preprocessing.py
syndp/timedp_algorithm.py
syndp-0.4.0.dist-info/LICENSE.txt
syndp-0.4.0.dist-info/METADATA
syndp-0.4.0.dist-info/WHEEL
syndp-0.4.0.dist-info/top_level.txt
syndp-0.4.0.dist-info/RECORD
